javad/__init__.py
javad/exports.py
javad/main.py
javad/processor.py
javad/stream.py
javad/utils.py
javad/assets/__init__.py
javad/assets/balanced.pt
javad/assets/mel_filters.npz
javad/assets/precise.pt
javad/assets/tiny.pt
javad/extras/__init__.py
javad/extras/audio.py
javad/extras/basic.py
javad/extras/trainer.py
javad-0.2.0.dist-info/LICENSE
javad-0.2.0.dist-info/METADATA
javad-0.2.0.dist-info/WHEEL
javad-0.2.0.dist-info/top_level.txt
javad-0.2.0.dist-info/RECORD
