Metadata-Version: 2.2
Name: javad
Version: 0.2.0
Summary: JaVAD: Just Another Voice Activity Detector
Author-email: Sergey Skrebnev <sergey.skrebnev@gmail.com>
License: MIT License
Project-URL: Homepage, https://github.com/skrbnv/javad
Project-URL: Documentation, https://javad.readthedocs.io/en/latest/
Classifier: Intended Audience :: Developers
Classifier: License :: OSI Approved :: MIT License
Classifier: Programming Language :: Python :: 3
Classifier: Programming Language :: Python :: 3.8
Requires-Python: >=3.8
License-File: LICENSE
Requires-Dist: torch>=2.0.0
Requires-Dist: numpy>=1.20.0
Provides-Extra: extras
Requires-Dist: soundfile>=0.12.0; extra == "extras"
Requires-Dist: spgdataset>=0.0.2; extra == "extras"
Requires-Dist: torchvision>=0.10.0; extra == "extras"
Requires-Dist: tqdm; extra == "extras"
Provides-Extra: doc
Requires-Dist: sphinx; extra == "doc"
Provides-Extra: test
Requires-Dist: pytest>=7.0; extra == "test"
Requires-Dist: pytest-cov>=4.0; extra == "test"
